clashbyte/__init__.py
clashbyte/apis.py
clashbyte/toolbox.py
clashbyte-0.0.5.dist-info/LICENSE
clashbyte-0.0.5.dist-info/METADATA
clashbyte-0.0.5.dist-info/WHEEL
clashbyte-0.0.5.dist-info/top_level.txt
clashbyte-0.0.5.dist-info/RECORD
