Metadata-Version: 2.1
Name: clashbyte
Version: 0.0.5
Home-page: https://github.com/QIN2DIM/ClashByte
Author: QIN2DIM
Author-email: yaoqinse@gmail.com
License: MIT
Keywords: clashbyte,clash,clash-meta,clashapi
Classifier: Topic :: Scientific/Engineering
Classifier: Topic :: Scientific/Engineering :: Artificial Intelligence
Classifier: Topic :: Software Development
Classifier: Topic :: Software Development :: Libraries
Classifier: Topic :: Software Development :: Libraries :: Python Modules
Classifier: License :: OSI Approved :: Apache Software License
Classifier: Programming Language :: Python :: 3
Requires-Python: >=3.8
License-File: LICENSE
Requires-Dist: loguru (>=0.7.0)
Requires-Dist: httpx (>=0.24.1)
Provides-Extra: dev
Requires-Dist: nox ; extra == 'dev'
Requires-Dist: pytest ; extra == 'dev'
Provides-Extra: test
Requires-Dist: pytest ; extra == 'test'
Requires-Dist: black ; extra == 'test'
